rivals_top8_results/__init__.py
rivals_top8_results/draw_example.py
rivals_top8_results/draw_recolors.py
rivals_top8_results/draw_results.py
rivals_top8_results/Resources/Backgrounds/Aether High/1.png
rivals_top8_results/Resources/Backgrounds/Aethereal Gates/1.png
rivals_top8_results/Resources/Backgrounds/Aethereal Gates/2.png
rivals_top8_results/Resources/Backgrounds/Air Armada/1.png
rivals_top8_results/Resources/Backgrounds/Air Armada/2.png
rivals_top8_results/Resources/Backgrounds/Blazing Hideout/1.png
rivals_top8_results/Resources/Backgrounds/Blazing Hideout/2.png
rivals_top8_results/Resources/Backgrounds/Fire Capital/1.png
rivals_top8_results/Resources/Backgrounds/Fire Capital/2.png
rivals_top8_results/Resources/Backgrounds/Frozen Fortress/1.png
rivals_top8_results/Resources/Backgrounds/Frozen Gates/1.png
rivals_top8_results/Resources/Backgrounds/Frozen Gates/2.png
rivals_top8_results/Resources/Backgrounds/Julesvale/1.png
rivals_top8_results/Resources/Backgrounds/Julesvale/2.png
rivals_top8_results/Resources/Backgrounds/Merchant Port/1.png
rivals_top8_results/Resources/Backgrounds/Merchant Port/2.png
rivals_top8_results/Resources/Backgrounds/Neo Fire Capital/1.png
rivals_top8_results/Resources/Backgrounds/Pridemoor Keep/1.png
rivals_top8_results/Resources/Backgrounds/Tempest Peak/1.png
rivals_top8_results/Resources/Backgrounds/The CEO Ring/1.png
rivals_top8_results/Resources/Backgrounds/The Endless Abyss/1.png
rivals_top8_results/Resources/Backgrounds/The Forest Floor/1.png
rivals_top8_results/Resources/Backgrounds/The RoA Ring/1.png
rivals_top8_results/Resources/Backgrounds/The Rock Wall/1.png
rivals_top8_results/Resources/Backgrounds/The Rock Wall/2.png
rivals_top8_results/Resources/Backgrounds/The Spirit Tree/1.png
rivals_top8_results/Resources/Backgrounds/The Swampy Estuary/1.png
rivals_top8_results/Resources/Backgrounds/The Swampy Estuary/2.png
rivals_top8_results/Resources/Backgrounds/Tower of Heaven/1.png
rivals_top8_results-1.6.3.dist-info/LICENSE
rivals_top8_results-1.6.3.dist-info/METADATA
rivals_top8_results-1.6.3.dist-info/WHEEL
rivals_top8_results-1.6.3.dist-info/top_level.txt
rivals_top8_results-1.6.3.dist-info/RECORD
