Metadata-Version: 2.1
Name: rivals-top8-results
Version: 1.6.3
Summary: Small Pillow library useful in creating automatic Rivals of Aether Top 8 Results screens 
Home-page: https://github.com/Impasse52/rivals-top8-results
Author: Impasse52
Author-email: giuseppe.termerissa@gmail.com
License: UNKNOWN
Project-URL: Bug Tracker, https://github.com/Impasse52/rivals-top8-results/issues
Platform: UNKNOWN
Requires-Python: >=3.6
License-File: LICENSE
